django_lti_dynamic_registration-0.1.2.dist-info/licenses/LICENSE
lti_dynamic_registration/__init__.py
lti_dynamic_registration/constants.py
lti_dynamic_registration/types.py
lti_dynamic_registration/views.py
django_lti_dynamic_registration-0.1.2.dist-info/METADATA
django_lti_dynamic_registration-0.1.2.dist-info/WHEEL
django_lti_dynamic_registration-0.1.2.dist-info/top_level.txt
django_lti_dynamic_registration-0.1.2.dist-info/RECORD
